{
  "blogs": [
    {
      "title": "Opening Party!",
      "body": "Why do we use it?\nIt is a",
      "author": "yoshi",
      "id": "2"
    },
    {
      "id": "d2c5",
      "title": "Saving to db",
      "body": "1221 p",
      "author": "mario"
    }
  ],

  "users": [
    {
      "id": "1",
      "first_name": "Daniel",
      "last_name": "Sherry"
    },
    {
      "id": "2",
      "first_name": "Nicole",
      "last_name": "Sherry"
    },
    {
      "id": "3",
      "first_name": "Bisc",
      "last_name": "Puppy dog"
    }
  ],

  "products": [
    {
      "id": "1",
      "product": "Half day daycare",
      "price": 20,
      "details": "4 hours; 8a-12p or 12p-4p"
    },
    {
      "id": "2",
      "product": "Full day daycare",
      "price": 35,
      "details": "8 hours; 8a-4p"
    },
    {
      "id": "3",
      "product": "Boarding, 1 night",
      "price": 35,
      "details": "Drop off 5p, pickup by 9a"
    }
  ]
}
